SimplePushoverClient/__init__.py
SimplePushoverClient/exceptions.py
SimplePushoverClient/models.py
SimplePushoverClient/pushover.py
simplepushoverclient-0.1.0.dist-info/LICENSE
simplepushoverclient-0.1.0.dist-info/METADATA
simplepushoverclient-0.1.0.dist-info/WHEEL
simplepushoverclient-0.1.0.dist-info/RECORD
